<annotation>
	<folder>stream3</folder>
	<filename>stream3_49.jpg</filename>
	<path>/Users/hastingsji/Desktop/stream3/stream3_49.jpg</path>
	<source>
		<database>Unknown</database>
	</source>
	<size>
		<width>352</width>
		<height>240</height>
		<depth>3</depth>
	</size>
	<segmented>0</segmented>
	<object>
		<name>car</name>
		<pose>Unspecified</pose>
		<truncated>0</truncated>
		<difficult>0</difficult>
		<bndbox>
			<xmin>132</xmin>
			<ymin>63</ymin>
			<xmax>159</xmax>
			<ymax>82</ymax>
		</bndbox>
	</object>
	<object>
		<name>car</name>
		<pose>Unspecified</pose>
		<truncated>0</truncated>
		<difficult>0</difficult>
		<bndbox>
			<xmin>125</xmin>
			<ymin>50</ymin>
			<xmax>145</xmax>
			<ymax>65</ymax>
		</bndbox>
	</object>
</annotation>
