<annotation>
	<folder>cameraStills</folder>
	<filename>stream5_181.jpg</filename>
	<path>/Users/peterwei/Desktop/CitywideFootprinting/cameraStills/stream5_181.jpg</path>
	<source>
		<database>Unknown</database>
	</source>
	<size>
		<width>352</width>
		<height>240</height>
		<depth>3</depth>
	</size>
	<segmented>0</segmented>
	<object>
		<name>car</name>
		<pose>Unspecified</pose>
		<truncated>0</truncated>
		<difficult>0</difficult>
		<bndbox>
			<xmin>180</xmin>
			<ymin>101</ymin>
			<xmax>220</xmax>
			<ymax>138</ymax>
		</bndbox>
	</object>
	<object>
		<name>car</name>
		<pose>Unspecified</pose>
		<truncated>0</truncated>
		<difficult>0</difficult>
		<bndbox>
			<xmin>131</xmin>
			<ymin>141</ymin>
			<xmax>179</xmax>
			<ymax>200</ymax>
		</bndbox>
	</object>
	<object>
		<name>car</name>
		<pose>Unspecified</pose>
		<truncated>0</truncated>
		<difficult>0</difficult>
		<bndbox>
			<xmin>244</xmin>
			<ymin>122</ymin>
			<xmax>296</xmax>
			<ymax>155</ymax>
		</bndbox>
	</object>
</annotation>
